pose_estimation_recognition_utils_mediapipe/MediaPipePoseEstimationFrom3DFrame.py
pose_estimation_recognition_utils_mediapipe/MediaPipePoseNames.py
pose_estimation_recognition_utils_mediapipe/__init__.py
pose_estimation_recognition_utils_mediapipe-0.1.0b1.dist-info/METADATA
pose_estimation_recognition_utils_mediapipe-0.1.0b1.dist-info/WHEEL
pose_estimation_recognition_utils_mediapipe-0.1.0b1.dist-info/top_level.txt
pose_estimation_recognition_utils_mediapipe-0.1.0b1.dist-info/RECORD
