Metadata-Version: 2.4
Name: pose-estimation-recognition-utils-mediapipe
Version: 0.1.0b1
Summary: Classes for AI recognition on pose estimation data
Home-page: https://github.com/cobtras/pose-estimation-recognition-utils-mediapipe
Author: Jonas David Stephan, Chanyut Boonkhamsaen, Nathalie Dollmann
Author-email: j.stephan@system-systeme.de
License: Apache 2.0
Requires-Dist: setuptools>=70.0.0
Requires-Dist: mediapipe>=0.10.21
Requires-Dist: pose-estimation-recognition-utils>=0.3.0b1
Dynamic: author
Dynamic: author-email
Dynamic: description
Dynamic: home-page
Dynamic: license
Dynamic: requires-dist
Dynamic: summary
